render_block/__init__.py
render_block/backend.py
django_jinja_render_block-0.3.0.dist-info/METADATA
django_jinja_render_block-0.3.0.dist-info/WHEEL
django_jinja_render_block-0.3.0.dist-info/licenses/LICENSE
django_jinja_render_block-0.3.0.dist-info/RECORD
