Metadata-Version: 2.4
Name: django-jinja-render-block
Version: 0.3.0
Summary: Render the content of a specific block tag from a Jinja2 template.
Project-URL: Homepage, https://github.com/loopwerk/django-jinja-render-block/
Project-URL: Repository, https://github.com/loopwerk/django-jinja-render-block.git
Project-URL: Issues, https://github.com/loopwerk/django-jinja-render-block/issues
Author-email: Kevin Renskers <kevin@loopwerk.io>
License-Expression: MIT
License-File: LICENSE
Requires-Python: >=3.13
Requires-Dist: django-jinja>=2.11.0
